README.rst
setup.py
single_process/__init__.py
single_process/init.py
single_process.egg-info/PKG-INFO
single_process.egg-info/SOURCES.txt
single_process.egg-info/dependency_links.txt
single_process.egg-info/top_level.txt