Metadata-Version: 1.1
Name: single-process
Version: 2.4.1
Summary: limit python script just run a single process
Home-page: https://github.com/gu321/single_process
Author: zuroc
Author-email: xpure@foxmail.com
License: UNKNOWN
Platform: UNKNOWN
Classifier: Development Status :: 5 - Production/Stable
Classifier: Environment :: Web Environment
Classifier: Intended Audience :: Developers
Classifier: License :: OSI Approved :: Apache Software License
Classifier: Operating System :: OS Independent
Classifier: Programming Language :: Python
Classifier: Topic :: Internet
Classifier: Topic :: Software Development :: Libraries :: Python Modules
